gcell/__init__.py
gcell/_logging.py
gcell/_settings.py
gcell/_version.py
gcell/cell/__init__.py
gcell/cell/celltype.py
gcell/cell/mutincell.py
gcell/config/__init__.py
gcell/config/config.py
gcell/config/local_interpret.yaml
gcell/config/s3_interpret.yaml
gcell/dna/__init__.py
gcell/dna/genome.py
gcell/dna/hocomoco.py
gcell/dna/motif.py
gcell/dna/motif_utils.py
gcell/dna/mutation.py
gcell/dna/nr_motif_v1.py
gcell/dna/nr_motif_v2.py
gcell/dna/sequence.py
gcell/dna/track.py
gcell/ontology/__init__.py
gcell/ontology/pathway.py
gcell/protein/__init__.py
gcell/protein/_math.py
gcell/protein/af2.py
gcell/protein/data.py
gcell/protein/interpro.py
gcell/protein/mutations.py
gcell/protein/protein.py
gcell/protein/stringdb.py
gcell/protein/uniprot.py
gcell/rna/__init__.py
gcell/rna/gencode.py
gcell/rna/gene.py
gcell/rna/gtf.py
gcell/utils/__init__.py
gcell/utils/causal_lib.py
gcell/utils/lingam.py
gcell/utils/lingam.r
gcell/utils/pdb_viewer.py
gcell/utils/s3.py
gcell-0.1.1.dist-info/METADATA
gcell-0.1.1.dist-info/WHEEL
gcell-0.1.1.dist-info/top_level.txt
gcell-0.1.1.dist-info/RECORD
