Metadata-Version: 2.4
Name: gcell
Version: 0.1.1
Summary: A Python library that represents different entities in a cell
Author-email: Xi Fu <fuxialexander@gmail.com>
Maintainer-email: Xi Fu <fuxialexander@gmail.com>
License-Expression: MIT
Project-URL: Homepage, https://github.com/fuxialexander/gcell
Project-URL: Repository, https://github.com/fuxialexander/gcell
Classifier: Development Status :: 3 - Alpha
Classifier: Intended Audience :: Science/Research
Classifier: Natural Language :: English
Classifier: Programming Language :: Python :: 3.10
Classifier: Programming Language :: Python :: 3.11
Classifier: Programming Language :: Python :: 3.12
Classifier: Topic :: Scientific/Engineering :: Bio-Informatics
Requires-Python: >=3.10
Requires-Dist: biopython
Requires-Dist: genomespy
Requires-Dist: gprofiler-official
Requires-Dist: gradio
Requires-Dist: hydra-core
Requires-Dist: lingam
Requires-Dist: matplotlib
Requires-Dist: jupyter-packaging
Requires-Dist: MOODS-python
Requires-Dist: networkx
Requires-Dist: numpy
Requires-Dist: omegaconf
Requires-Dist: openpyxl
Requires-Dist: pandas
Requires-Dist: plotly
Requires-Dist: pooch
Requires-Dist: pyarrow
Requires-Dist: pyBigWig
Requires-Dist: pyfaidx
Requires-Dist: pyranges
Requires-Dist: requests
Requires-Dist: s3fs
Requires-Dist: scipy
Requires-Dist: seaborn
Requires-Dist: seqlogo
Requires-Dist: tqdm
Requires-Dist: xmlschema
Requires-Dist: zarr<3
Requires-Dist: nglview<4
Requires-Dist: py3Dmol
Provides-Extra: test
Requires-Dist: pytest>=8.2; extra == "test"
Requires-Dist: pytest-nunit; extra == "test"
Requires-Dist: pytest-mock; extra == "test"
Requires-Dist: pytest-cov; extra == "test"
Requires-Dist: profimp; extra == "test"
Provides-Extra: dev
Requires-Dist: setuptools_scm; extra == "dev"
Requires-Dist: pre-commit; extra == "dev"
Requires-Dist: towncrier; extra == "dev"
Requires-Dist: ipykernel; extra == "dev"
Requires-Dist: jupyter; extra == "dev"
Requires-Dist: jupyter-packaging; extra == "dev"
Requires-Dist: nglview; extra == "dev"
Requires-Dist: py3Dmol; extra == "dev"
Requires-Dist: nbsphinx; extra == "dev"
Requires-Dist: nbformat; extra == "dev"
Requires-Dist: snapatac2; extra == "dev"
Requires-Dist: scanpy; extra == "dev"
Requires-Dist: scikit-misc; extra == "dev"
Provides-Extra: doc
Requires-Dist: sphinx>=7; extra == "doc"
Requires-Dist: sphinx-book-theme>=1.1.0; extra == "doc"
Requires-Dist: scanpydoc>=0.14.1; extra == "doc"
Requires-Dist: sphinx-autodoc-typehints>=1.25.2; extra == "doc"
Requires-Dist: myst-parser>=2; extra == "doc"
Requires-Dist: myst-nb>=1.1.2; extra == "doc"
Requires-Dist: sphinx-design; extra == "doc"
Requires-Dist: sphinx-tabs; extra == "doc"
Requires-Dist: jupyter-packaging; extra == "doc"
Requires-Dist: readthedocs-sphinx-search; extra == "doc"
Requires-Dist: sphinxext-opengraph; extra == "doc"
Requires-Dist: sphinx-copybutton; extra == "doc"
Requires-Dist: nbsphinx>=0.9; extra == "doc"
Requires-Dist: ipython>=7.20; extra == "doc"
Requires-Dist: matplotlib!=3.6.1; extra == "doc"
Requires-Dist: sphinxcontrib-bibtex; extra == "doc"
Requires-Dist: setuptools; extra == "doc"
Requires-Dist: towncrier; extra == "doc"
Provides-Extra: gpu
Requires-Dist: culingam; extra == "gpu"
